README.md
setup.py
send2trash3k/__init__.py
send2trash3k.egg-info/PKG-INFO
send2trash3k.egg-info/SOURCES.txt
send2trash3k.egg-info/dependency_links.txt
send2trash3k.egg-info/top_level.txt